bcdoc/__init__.py
bcdoc/compat.py
bcdoc/docevents.py
bcdoc/docstringparser.py
bcdoc/restdoc.py
bcdoc/style.py
bcdoc/textwriter.py
bcdoc-0.15.0.dist-info/DESCRIPTION.rst
bcdoc-0.15.0.dist-info/METADATA
bcdoc-0.15.0.dist-info/pydist.json
bcdoc-0.15.0.dist-info/RECORD
bcdoc-0.15.0.dist-info/top_level.txt
bcdoc-0.15.0.dist-info/WHEEL
